samhiqmailer/SamhiqMailer.py
samhiqmailer/__init__.py
samhiqmailer/resources/icon.png
samhiqmailer-3.2.dist-info/licenses/LICENSE
samhiqmailer-3.2.dist-info/METADATA
samhiqmailer-3.2.dist-info/WHEEL
samhiqmailer-3.2.dist-info/entry_points.txt
samhiqmailer-3.2.dist-info/top_level.txt
samhiqmailer-3.2.dist-info/RECORD
