Metadata-Version: 2.4
Name: samhiqmailer
Version: 3.2
Summary: Professional Bulk Email Client with Modern UI and Advanced Features
Home-page: https://github.com/samhiq/SamhiqMailer
Author: Md Sameer Iqbal
Author-email: contact.samhiq@gmail.com
Classifier: Development Status :: 5 - Production/Stable
Classifier: Intended Audience :: End Users/Desktop
Classifier: Operating System :: OS Independent
Classifier: Topic :: Communications :: Email
Requires-Python: >=3.6
License-File: LICENSE
Requires-Dist: PyQt5>=5.15.0
Requires-Dist: openpyxl>=3.0.0
Requires-Dist: requests>=2.25.0
Dynamic: author
Dynamic: author-email
Dynamic: classifier
Dynamic: description
Dynamic: description-content-type
Dynamic: home-page
Dynamic: license-file
Dynamic: requires-dist
Dynamic: requires-python
Dynamic: summary
